HTTP/2.0 200 OK
Alt-Svc: hq=":443"; ma=2592000; quic=51303431; quic=51303339; quic=51303338; quic=51303337; quic=51303335,quic=":443"; ma=2592000; v="41,39,38,37,35"
Cache-Control: no-cache, must-revalidate
Content-Type: text/xml; charset=UTF-8
Date: Fri, 12 Jan 2018 16:35:58 GMT
Expires: Fri, 01 Jan 1990 00:00:00 GMT
Pragma: no-cache
Server: video-timedtext
X-Content-Type-Options: nosniff
X-Frame-Options: SAMEORIGIN
X-Xss-Protection: 1; mode=block

<?xml version="1.0" encoding="utf-8" ?><transcript><text start="30.838" dur="2.933">该怎么面对熊世家啊</text><text start="33.771" dur="1">应该装得很自然的</text><text start="34.771" dur="2.233">问声早就好了吧</text><text start="37.004" dur="3.767">还是当作什么都没发生过</text><text start="56.972" dur="1.866">姊</text><text start="58.838" dur="1.6">贺一美</text><text start="60.438" dur="1.3">干嘛</text><text start="61.738" dur="2.067">妳干嘛那么激动啊</text><text start="64.738" dur="1.067">没有啊</text><text start="65.805" dur="0.9">怎么了</text><text start="66.705" dur="3.533">妳在这边一前一后... </text><text start="70.238" dur="1.899">是要跳恰恰哦</text><text start="72.137" dur="2.501">我刚刚在想一些事情</text><text start="77.004" dur="1.133">熊主任</text><text start="78.137" dur="0.735">早</text><text start="78.872" dur="2.265">早安</text><text start="84.805" dur="1.9">姊，妳要去哪儿啊</text><text start="86.705" dur="1.233">买早餐</text><text start="87.938" dur="2.133">买早餐</text><text start="90.071" dur="2.133">刚刚不是才在家里吃过早餐吗</text><text start="98.972" dur="2.332">熊主任</text><text start="101.304" dur="4">我姊她不会是在躲你吧</text><text start="106.605" dur="1.933">应该是吧</text><text start="108.538" dur="1.033">为什么</text><text start="109.571" dur="2.267">发生什么事啊</text><text start="111.838" dur="1.867">这个... </text><text start="113.705" dur="1.966">问妳姊吧</text><text start="120.271" dur="2.1">姊真是越来越奇怪了</text><text start="122.938" dur="1">差在哪里</text><text start="123.938" dur="0.833">这里</text><text start="124.771" dur="1.4">就是差在这一块</text><text start="126.171" dur="1.634">会让你瞬间变成一百九</text><text start="127.805" dur="0.833">变得更高</text><text start="128.638" dur="0.867">跟他一样，你看</text><text start="129.505" dur="1.1">很好啊</text><text start="130.605" dur="1.233">只是妳顺序</text><text start="131.838" dur="2.333">顺序有点错误有点错误</text><text start="134.171" dur="0.933">如果我变换指法</text><text start="135.104" dur="1.434">这样会很奇怪吗</text><text start="136.538" dur="1.133">就是指法会变啊</text><text start="137.671" dur="1.5">妳可能不会那么顺</text><text start="139.171" dur="1.1">譬如說妳一个手指头</text><text start="140.271" dur="2.033">就可以换到下一个和弦</text><text start="142.304" dur="0.8">就是它会有... </text><text start="143.104" dur="3.634">而且它本来就有和谐的问题</text><text start="148.838" dur="1.1">陈龙飞</text><text start="149.938" dur="1.733">你吉他弹得很厉害吗</text><text start="151.671" dur="1.034">还可以教人</text><text start="152.705" dur="2.399">真的、假的啊</text><text start="155.104" dur="0.634">真的哦</text><text start="155.738" dur="1.5">他不但吉他弹得好</text><text start="157.238" dur="2.066">也教得很好</text><text start="159.304" dur="1.1">我可以作证哦</text><text start="160.404" dur="2.401">陈龙飞，他还会自己作曲哦</text><text start="164.471" dur="0.967">既然这样</text><text start="165.438" dur="1.233">弹一首来听听吧</text><text start="166.671" dur="1.167">我真的满想听看看</text><text start="167.838" dur="1.633">你弹得怎么样</text><text start="169.471" dur="1.034">我也想听</text><text start="170.505" dur="1.566">好啊</text><text start="185.638" dur="3.2">别害怕未来上了锁</text><text start="188.838" dur="3.266">别犹豫先出发再说</text><text start="192.104" dur="1.634">不啰嗦</text><text start="193.738" dur="0.633">扬起帆</text><text start="194.371" dur="4.234">五味杂陈都是种享受</text><text start="198.605" dur="3.399">把罗盘挂起当时钟</text><text start="202.004" dur="3.2">别害怕他们怎么说</text><text start="205.204" dur="1.701">相信我</text><text start="206.905" dur="1.199">地球是圆的</text><text start="208.104" dur="4.033">只要大胆往前走</text><text start="212.137" dur="3.401">风雨是命运的安排</text><text start="215.538" dur="3.3">让我们去放手一搏</text><text start="218.838" dur="0.633"> BE HAPPY </text><text start="219.471" dur="3.067"> WE ARE NOT ALONE </text><text start="223.738" dur="3.1">我们是一千个太阳</text><text start="226.838" dur="3.7">要去闯世界尽头迎风破浪</text><text start="230.538" dur="4.566">追彩虹精灵的宝藏</text><text start="236.171" dur="3.2">我们是一千个太阳</text><text start="239.371" dur="3.733">要照亮宇宙星球四面八方</text><text start="243.104" dur="4.601">手牵手晒暖了梦想</text><text start="248.805" dur="3.133">我们是一千个太阳</text><text start="251.938" dur="3.7">要去闯世界尽头迎风破浪</text><text start="255.638" dur="5.334">追彩虹精灵的宝藏</text><text start="261.538" dur="3.2">我们是一千个太阳</text><text start="264.738" dur="3.533">要照亮宇宙星球四面八方</text><text start="268.271" dur="5.1">手牵手晒暖了梦想</text><text start="273.371" dur="3.434">冒险在等我们分享</text><text start="284.571" dur="1.733">超帅的</text><text start="286.304" dur="2.401">陈龙飞真的弹得很好吧</text><text start="288.705" dur="1.499">我对你更刮目相看了</text><text start="290.204" dur="1.1">不但会游泳</text><text start="291.304" dur="2.134">又会弹吉他又会唱歌</text><text start="293.438" dur="2.1">应该很多女生追你吧</text><text start="298.404" dur="2.167">妳也唱得很好听啊</text><text start="300.571" dur="0.667">对啊</text><text start="301.238" dur="3.533">言馨是二B班最会唱歌的</text><text start="304.771" dur="1.233">不只是二B班</text><text start="306.004" dur="2.4">言馨唱歌是全校最好听的</text><text start="308.404" dur="1.234">妳也太夸张了吧</text><text start="311.505" dur="2.033">威哥</text><text start="313.538" dur="2.067">你什么时候比赛啊</text><text start="315.605" dur="2.033">这个周末就要比赛了</text><text start="317.638" dur="1.133">你放心</text><text start="318.771" dur="2.101">我会一场一场的往上爬</text><text start="320.872" dur="1.933">最后打进决赛</text><text start="326.004" dur="0.767">走吧</text><text start="335.505" dur="3">曹教官，下课了</text><text start="338.505" dur="1.1">坐，辛苦了</text><text start="339.605" dur="1.333">来...妳进来就好了</text><text start="340.938" dur="1.767">对</text><text start="342.705" dur="2">好</text><text start="344.705" dur="2.066">曹教官，辛苦了，今天</text><text start="348.538" dur="0.666">曹教官，妳不要忘了</text><text start="349.204" dur="2.634">我们周末的约会哦</text><text start="351.838" dur="2">杜组长，我们是去买东西</text><text start="353.838" dur="1.299">不是约会</text><text start="355.137" dur="2.9">你这样子讲别人会误会的</text><text start="358.037" dur="1.668">反正这边没人嘛</text><text start="359.705" dur="1.466">我知道</text><text start="361.171" dur="1.6">我们是那个约定会面</text><text start="362.771" dur="2.201">不是约会</text><text start="364.972" dur="1.099">曹教官，如果... </text><text start="366.071" dur="1.767">周末我们买完东西</text><text start="367.838" dur="0.633">如果快的话</text><text start="368.471" dur="0.501">有时间的话</text><text start="368.972" dur="1.332">我们还可以... </text><text start="370.304" dur="1.401">还可以吃个饭</text><text start="371.705" dur="0.833">那如果吃饭吃快一点</text><text start="372.538" dur="0.566">如果有时间</text><text start="373.104" dur="0.9">我们可以去看个电影</text><text start="374.004" dur="1.334">杜组长，不好意思</text><text start="375.338" dur="1.866">我没有太多时间待在外面</text><text start="377.204" dur="1.867">我还有很多公务要处理</text><text start="379.071" dur="1.6">这样子啊</text><text start="380.671" dur="1.5">可是妳就算再忙</text><text start="382.171" dur="0.567">也不可能说</text><text start="382.738" dur="1.867">连吃饭的时间都没有嘛</text><text start="384.605" dur="0.333">对不对</text><text start="384.938" dur="2.767">我们吃个饭不会花太多时间的</text><text start="387.705" dur="0.8">可是我真的... </text><text start="388.505" dur="1.766">我跟妳保证好不好</text><text start="390.271" dur="0.9">就是吃完之后</text><text start="391.171" dur="1.067">我们就鸟兽散</text><text start="392.238" dur="0.899">就各自回家</text><text start="393.137" dur="1.801">我绝对不会耽误妳太多时间的</text><text start="394.938" dur="1.5">就吃个饭而已</text><text start="396.438" dur="0.566">就算妳不吃</text><text start="397.004" dur="2.1">妳回去还是要自己弄了吃嘛</text><text start="399.104" dur="1.1">我们就在外面一起吃了嘛</text><text start="400.204" dur="2.167">吃完我们就散、就撤</text><text start="402.371" dur="2.033">好不好，可以吧</text><text start="405.538" dur="1.267">那好吧</text><text start="406.805" dur="1.399">你带我去买东西</text><text start="408.204" dur="1.234">我请你吃饭</text><text start="409.438" dur="1.1">表示谢意</text><text start="410.538" dur="1.133">不用那么客气</text><text start="411.671" dur="2.134">这个到时候再说</text><text start="413.805" dur="2.332">那就这么说定了，周末</text><text start="416.137" dur="2.735">十点，十</text><text start="421.605" dur="2">追女孩子就是这样子</text><text start="423.605" dur="2.066">首要就是攻心</text><text start="425.671" dur="2.6">恒心、耐心、爱心</text><text start="428.271" dur="1.234">我都有</text><text start="429.505" dur="2.699">好的开始就是成功的... </text><text start="435.671" dur="1.567">贺老师，下课了</text><text start="441.271" dur="1.167">这么急着干什么</text><text start="442.438" dur="1.467">慌慌张张的逃难啊</text><text start="443.905" dur="2.399">世界末日啊</text><text start="446.304" dur="0.8">我有急事</text><text start="447.104" dur="1.467">有急事啊</text><text start="448.571" dur="1.533">真是借口都想好了</text><text start="450.104" dur="3.2">昨天是身体不舒服</text><text start="453.304" dur="1.434">今天是有急事</text><text start="454.738" dur="1.067">那明天的想好没有</text><text start="455.805" dur="1.966">明天没想好我可以帮妳想</text><text start="457.771" dur="2.067">我有...有急事、不舒服</text><text start="459.838" dur="0.9">我也不舒服、有急事</text><text start="460.738" dur="0.9">都可以杜组长</text><text start="461.638" dur="1.267">我赶时间</text><text start="462.905" dur="0.733">又赶时间了</text><text start="463.638" dur="2.867">既然这样子，我送妳</text><text start="470.605" dur="2.666">躲得了一时，躲不了一世...家</text><text start="473.271" dur="2.601">加油... </text><text start="475.872" dur="0.966">给你十个赞</text><text start="478.505" dur="1.3">闪啦</text><text start="482.304" dur="3.1">我送妳回去，顺路啊</text><text start="485.404" dur="1.9">顺路</text><text start="487.304" dur="2.034">我们家又住不同方向</text><text start="489.338" dur="1.733">我是专程来送妳回去的</text><text start="491.071" dur="1">所以妳要去的地方</text><text start="492.071" dur="1.767">就是我要去的地方</text><text start="493.838" dur="1.867">那就顺路</text><text start="495.705" dur="1.499">果然是熊主任</text><text start="497.204" dur="2.668">招招毙命，厉害</text><text start="502.771" dur="1.266">不用麻烦了啦</text><text start="504.037" dur="1.901">我自己回去就可以了</text><text start="513.771" dur="1.266">我想送妳回去</text><text start="515.037" dur="1.334">走吧</text><text start="519.571" dur="1.667">曹教官... </text><text start="524.638" dur="1.833">闪啊</text><text start="527.972" dur="2.099">好闪啊</text><text start="531.838" dur="2">不过这熊主任这样也不对</text><text start="533.838" dur="1.166">女孩子都说不要... </text><text start="535.004" dur="1.2">他硬要</text><text start="536.204" dur="0.701">这么粗鲁</text><text start="536.905" dur="3.033">也不想一下女孩子的感受</text><text start="539.938" dur="1.099">不会啊</text><text start="541.037" dur="3.668">我倒觉得这样满有男子气概的</text><text start="547.037" dur="1.334">是哦</text><text start="548.371" dur="0.601">所以曹教官</text><text start="548.972" dur="3">妳是喜欢男孩子粗鲁</text><text start="551.972" dur="0.933">不是</text><text start="552.905" dur="2.666">霸气、MAN的一面是不是</text><text start="569.838" dur="3.166">走，曹教官</text><text start="573.004" dur="1.167">我们去吃饭</text><text start="581.505" dur="1.367">等一下... </text><text start="582.872" dur="2.366">等一下</text><text start="585.238" dur="2">痛... </text><text start="597.972" dur="1.099">熊世家</text><text start="599.671" dur="1.533">放手</text><text start="603.004" dur="1.501">现在在校园里面</text><text start="604.505" dur="1.3">我们身为老师的</text><text start="605.805" dur="2.133">这样拉拉扯扯是能看吗</text><text start="607.938" dur="0.567">妳大方一点</text><text start="608.505" dur="1.666">我就不用这样做了</text><text start="611.404" dur="0.834">那... </text><text start="612.238" dur="1.766">我承认</text><text start="614.004" dur="1.334">你突然跟我告白</text><text start="615.338" dur="2">我有点不知所措</text><text start="617.338" dur="2.233">而且我们在同一个地方上班</text><text start="619.571" dur="2.167">这样会很尴尬</text><text start="623.171" dur="2.5">这句话我放在心里面很久了</text><text start="625.671" dur="1.1">直到那一天</text><text start="626.771" dur="2">我才有勇气说出来</text><text start="629.938" dur="3.133">我不想再隐藏我对妳的感情了</text><text start="635.638" dur="1.433">不過妳放心</text><text start="637.071" dur="1.167">我不是要逼妳接受</text><text start="638.238" dur="2.267">或者是马上给我答案</text><text start="640.505" dur="1.866">妳可以慢慢想</text><text start="642.371" dur="1">我只是不要妳这么辛苦的</text><text start="643.371" dur="1.567">躲着我</text><text start="647.705" dur="1.666">我也没有躲成功</text><text start="649.371" dur="1.501">不是吗</text><text start="653.538" dur="1.133">好</text><text start="654.671" dur="1.7">在妳给我答案之前</text><text start="656.371" dur="1.534">我想</text><text start="657.905" dur="1.8">我们就跟平常相处一样</text><text start="659.705" dur="1.599">还是同事</text><text start="661.304" dur="0.833">在公事上面</text><text start="662.137" dur="1.9">我们照规定来处理</text><text start="664.037" dur="1.768">在学生的辅导上面</text><text start="665.805" dur="1.966">我们互相协助</text><text start="667.771" dur="1.433">这样子大家都轻松</text><text start="669.204" dur="1.367">好吗</text><text start="671.705" dur="2.633">好，你说的哦</text><text start="674.338" dur="1.534">既然我们说清楚了</text><text start="675.872" dur="2.699">那以后在学校就是好同事</text><text start="686.004" dur="0.934">还是好朋友</text><text start="690.09" dur="2.668"> OK，也是好朋友</text><text start="694.524" dur="1.134">既然是好朋友</text><text start="695.658" dur="2.399">我送妳回家应该没问题吧</text><text start="700.558" dur="1.499">我为什么觉得</text><text start="702.057" dur="1.567">我好像上当啦</text><text start="704.591" dur="1.566">妳是要我像刚刚那样子</text><text start="706.157" dur="2.134">在大家面前拖着妳走</text><text start="708.291" dur="2.533">还是要上我这个好朋友的车呢</text><text start="737.558" dur="1.233">包贝尔</text><text start="738.791" dur="1.134">我刚洗好澡</text><text start="740.457" dur="2.767">放心，这水是干净的啦</text><text start="743.224" dur="1.267">干净的又怎么样</text><text start="744.491" dur="1">我明天要比赛耶</text><text start="745.491" dur="1.666">你在泼我冷水</text><text start="747.157" dur="1.267">这是泰国祈福法</text><text start="748.424" dur="0.933">你不知道吗</text><text start="749.357" dur="0.767">我泼你的水越多</text><text start="750.124" dur="2">就代表我对你祝福越多嘛</text><text start="752.124" dur="1.4">你不懂一直念</text><text start="753.524" dur="0.633">奇怪</text><text start="754.157" dur="1.134">好，来，再泼你一点</text><text start="756.124" dur="1.567">好了</text><text start="757.691" dur="0.666">这种祈福法</text><text start="758.357" dur="2.201">以后用到体育课以后嘛</text><text start="760.558" dur="1.766">你以为只有这样子是不是</text><text start="762.324" dur="1.234">马桶</text><text start="763.558" dur="1.433">还有这些哦</text><text start="766.925" dur="2.899">结合庙宇祈福过后的挂饰</text><text start="769.824" dur="2">还有来自各个庙宇的平安符</text><text start="771.824" dur="1.7">来，戴好... </text><text start="773.524" dur="1.2">手链</text><text start="774.724" dur="2.201">来，保证你戴上它之后</text><text start="776.925" dur="2.232">好运一路相随</text><text start="779.157" dur="2.234">明天的比赛一定旗开得胜</text><text start="785.357" dur="2.134">这个也是平安符吗</text><text start="788.724" dur="1.567">中西合并嘛</text><text start="790.291" dur="1.166">多多益善</text><text start="791.457" dur="1.633">神就要多拜</text><text start="793.09" dur="0.967">多保庇啰</text><text start="794.057" dur="1.234">保佑... </text><text start="795.958" dur="1.299">保佑... </text><text start="798.858" dur="1.167">我是去比赛</text><text start="800.025" dur="1.633">我又不是去选美</text><text start="801.658" dur="1.666">戴这么多东西</text><text start="803.324" dur="1.833">看起来很弱耶</text><text start="805.925" dur="1.866">这些东西我不需要啦</text><text start="808.991" dur="2.034">很没有气势耶</text><text start="811.025" dur="0.966">我只需要你们两个</text><text start="811.991" dur="1.7">诚心的祝福跟加油</text><text start="813.691" dur="1.8">我就可以所向无敌了</text><text start="815.491" dur="2.2">威哥，我们一定支持你到底</text><text start="817.691" dur="1.1">陪你进总决赛</text><text start="818.791" dur="1.566">拿冠军</text><text start="821.291" dur="2.066">我一向运气都不错</text><text start="823.357" dur="2.267">明天应该会顺利的</text><text start="825.624" dur="0.833">所以我们两个</text><text start="826.457" dur="2.234">是威哥的吉祥物啰</text><text start="829.257" dur="1">其实我觉得</text><text start="830.257" dur="2.967">你应该是威哥的沙包</text><text start="835.09" dur="1">揍啊</text><text start="837.758" dur="0.966">好了... </text><text start="843.624" dur="2.2">不能忘记水壶</text><text start="845.824" dur="1.934">还有毛巾</text><text start="848.591" dur="0.566">马桶，你想一下</text><text start="849.157" dur="1.1">威哥还有什么东西没带</text><text start="850.257" dur="1.534">都有放在里面了</text><text start="851.791" dur="0.967">受伤用的药膏</text><text start="852.758" dur="1.299">你赶快找一下</text><text start="855.124" dur="1.734">你们两个紧张什么啊</text><text start="856.858" dur="2.067">比赛的是我又不是你们</text><text start="858.925" dur="3.265">威哥，我们两个很担心你啊</text><text start="862.19" dur="2.534">放心啦，我不会让你失望</text><text start="864.724" dur="1.4">等一下在比赛上</text><text start="866.124" dur="1.133">就看我怎么赢吧</text><text start="867.257" dur="1.833">没错，威哥必胜</text><text start="869.09" dur="1.201">我们要给威哥自信</text><text start="870.291" dur="1.1">他等一下就可以来个帅气的</text><text start="871.391" dur="1.2">左勾拳还有右勾拳</text><text start="874.357" dur="0.634">不好意思</text><text start="874.991" dur="1.099">不好意思</text><text start="879.424" dur="1.867">你是不是故意的啊</text><text start="881.291" dur="0.799">黑仔</text><text start="882.09" dur="1.835">是你走路不长眼睛吧</text><text start="883.925" dur="1.733">你到底在讲什么啊</text><text start="885.658" dur="1.833">怎样</text><text start="887.491" dur="1.534">不要理他</text><text start="898.025" dur="1.499">算了，我们走</text><text start="902.157" dur="1.601">谁啊，嚣张成这样</text><text start="903.758" dur="1.066">就是嘛</text><text start="906.324" dur="1.9">不用跟他们计较</text><text start="908.224" dur="1.5">我们参加的是正当的比赛</text><text start="909.724" dur="1.767">不要在外面惹事</text><text start="911.491" dur="1.599">擂台上讨回来就好</text><text start="913.09" dur="1.634">威哥说得对</text><text start="914.724" dur="2.034">赢家通常都是低调的啊</text><text start="919.524" dur="2.967"> (泰国咒语) </text><text start="934.724" dur="2.466">这次的对手竟然是他耶</text><text start="937.19" dur="1.167">不过他看起来还好</text><text start="938.357" dur="1.201">没有什么杀伤力</text><text start="939.558" dur="2.033">那也不能轻敌啊</text><text start="941.591" dur="1.434">威哥</text><text start="943.025" dur="0.966">你看</text><text start="943.991" dur="1.8">他旁边的人在教他耶</text><text start="945.791" dur="1.7">感觉满厉害的</text><text start="947.491" dur="1.633">我刚刚去打听了一下</text><text start="949.124" dur="2.767">他好像也是这次的比赛选手</text><text start="951.891" dur="0.333">等一下</text><text start="952.224" dur="1.966">如果对手看起来很弱的话</text><text start="954.19" dur="2.501">你还是不能轻敌哦</text><text start="956.691" dur="1.033">我知道</text><text start="962.658" dur="2.1">看来这次比赛</text><text start="964.758" dur="2.499">最棘手的对手就是他</text><text start="971.878" dur="2.133">成吉思汗杯第一场比赛</text><text start="974.011" dur="1.933">红方选手郑明威</text><text start="975.944" dur="1.668">蓝方选手冯志甲</text><text start="977.612" dur="1.366">请双方选手入场</text><text start="990.378" dur="0.8">开始</text><text start="991.178" dur="4.867">加油... </text><text start="998.745" dur="4.7">加油... </text><text start="1009.145" dur="6.1">加油... </text><text start="1018.412" dur="4.499">加油... </text><text start="1029.512" dur="1.033">好棒</text><text start="1032.378" dur="1.2">倒... </text><text start="1042.944" dur="1.134">威哥好棒</text><text start="1057.745" dur="2">帅哦... </text><text start="1060.911" dur="1.2">好湿哦</text><text start="1062.111" dur="0.867">走了</text><text start="1065.345" dur="1.133">威哥，你真的超厉害</text><text start="1066.478" dur="2.733">第一场就赢了耶</text><text start="1069.211" dur="1.767">郑明威</text><text start="1070.978" dur="1.167">你不要太嚣张</text><text start="1072.145" dur="0.733">我们家天泉</text><text start="1072.878" dur="1.867">一拳就可以击倒你</text><text start="1074.745" dur="0.6">我跟你讲</text><text start="1075.345" dur="2.133">我们家天泉可是上届的冠军</text><text start="1077.478" dur="0.5">他的纪录</text><text start="1077.978" dur="2.033">到现在为止都没有人打得破</text><text start="1080.011" dur="1.634">我劝你还是多买一些保险吧</text><text start="1081.645" dur="1.533">保证用得到</text><text start="1083.178" dur="1.601"> (泰语) 你阿嬷十八岁</text><text start="1090.911" dur="1.501">你是我终极的目标</text><text start="1092.412" dur="2.799">你放心，我一定会打败你</text><text start="1095.211" dur="1.6">等你打到最后再说吧</text></transcript>