HTTP/2.0 200 OK
Alt-Svc: hq=":443"; ma=2592000; quic=51303431; quic=51303339; quic=51303338; quic=51303337; quic=51303335,quic=":443"; ma=2592000; v="41,39,38,37,35"
Cache-Control: no-cache, must-revalidate
Content-Type: text/xml; charset=UTF-8
Date: Fri, 12 Jan 2018 16:35:30 GMT
Expires: Fri, 01 Jan 1990 00:00:00 GMT
Pragma: no-cache
Server: video-timedtext
X-Content-Type-Options: nosniff
X-Frame-Options: SAMEORIGIN
X-Xss-Protection: 1; mode=block

<?xml version="1.0" encoding="utf-8" ?><transcript><text start="21.509" dur="1.599">天啊</text><text start="23.108" dur="1.601">穿那么厚的衣服</text><text start="24.709" dur="2.499">被打到还是超痛的耶</text><text start="27.208" dur="1.034">威哥</text><text start="28.242" dur="2.167">我真的超想跟你一组的</text><text start="30.409" dur="0.966">你真的超强</text><text start="31.375" dur="3">一发都没被打到</text><text start="34.375" dur="2.1">今天委屈你了</text><text start="43.475" dur="0.767">要不是马桶</text><text start="44.242" dur="1.066">他行动迟缓的话</text><text start="45.308" dur="1.334">你早就变成蜂窝了</text><text start="46.642" dur="2.033">你应该要好好感谢马桶</text><text start="48.675" dur="1.4">我哪是行动迟缓</text><text start="50.075" dur="1.033">我是因为体型的关系</text><text start="51.108" dur="1.434">目标比较明确</text><text start="52.542" dur="0.7">对啊</text><text start="53.242" dur="2">我们两个就算躲在障碍物后面</text><text start="55.242" dur="1.433">还是会露出半个手臂</text><text start="56.675" dur="0.867">哪像你们啊</text><text start="57.542" dur="2.167">一个个都比缩头乌龟还缩</text><text start="59.709" dur="1.466">我就知道妳懂</text><text start="61.175" dur="0.5">是啊</text><text start="61.675" dur="1.533">为了弥补我受创的心灵</text><text start="63.208" dur="1.301">我要怒吃三碗面线</text><text start="64.509" dur="1.2">再四碗肉圆</text><text start="65.709" dur="0.599">老板</text><text start="66.308" dur="0.7">有没有体重机啊哪会啊</text><text start="67.008" dur="2.701">很饿，好不好各位要点餐了吗</text><text start="69.709" dur="1.167">我要大肠面线</text><text start="70.876" dur="1.132">还有深坑臭豆腐</text><text start="72.008" dur="1.234">还有嘉义东石蚵仔煎</text><text start="73.242" dur="1.333">还有... 等一下</text><text start="74.575" dur="2.267">雨晴，妳之前有来过这里哦</text><text start="76.842" dur="0.767">妳都没有看菜单</text><text start="77.609" dur="1">妳怎么知道要点什么啊</text><text start="78.609" dur="0.9">对啊</text><text start="79.509" dur="0.833">我之前住的那边</text><text start="80.342" dur="1.333">就有分店啊</text><text start="81.675" dur="2.034">没有错，是不是</text><text start="83.709" dur="1.533">上次就跟你们讲过了嘛</text><text start="85.242" dur="2.433">我们老板可是很有经营头脑的</text><text start="87.675" dur="1.167">他知道开一家店</text><text start="88.842" dur="1.767">不只要东西好吃</text><text start="90.609" dur="2.733">当然还要兼顾一下小确幸</text><text start="93.342" dur="1.733">什么小确幸啊</text><text start="95.075" dur="0.866">小确幸啊</text><text start="95.941" dur="3.034">简单来说就是「小」小的资金</text><text start="98.975" dur="1.767"> 「确」实的开店指导</text><text start="100.742" dur="3.7">以及「幸」福的圆梦</text><text start="104.442" dur="1.499">听起来好像很威耶</text><text start="105.941" dur="0.935">我跟你们讲</text><text start="106.876" dur="1.599">我们现在连中部到北部</text><text start="108.475" dur="2.8">就超过五十家的加盟店啰</text><text start="111.275" dur="1.367">那我应该学这个老板</text><text start="112.642" dur="1.2">一样开店吧</text><text start="113.842" dur="1.633">那我就每天吃不完的美食了</text><text start="115.475" dur="0.667">赞成</text><text start="116.142" dur="1.4">贾飞燕，我建议妳不要</text><text start="117.542" dur="0.7">妳开店的话</text><text start="118.242" dur="1.567">店里面的东西都被妳吃垮了</text><text start="119.809" dur="1.766">那客人来要吃什么</text><text start="122.908" dur="1.467">太夸张了啦金小帅</text><text start="124.375" dur="1.167">满中肯的耶</text><text start="127.675" dur="1.567">好了，大家不要聊了</text><text start="129.242" dur="0.866">到底要点什么</text><text start="130.108" dur="0.567">快点好... </text><text start="130.675" dur="0.633">不要客气好不好</text><text start="131.308" dur="1.568">就三碗面线啊那个... </text><text start="132.876" dur="0.933">这边... </text><text start="135.475" dur="1.466">这家蚵仔煎好好吃哦</text><text start="136.941" dur="1.734">对啊</text><text start="138.675" dur="1.233">超级饱的程雨晴</text><text start="139.908" dur="0.834">这么晚了</text><text start="140.742" dur="1.199">妳对宿舍也不熟悉</text><text start="141.941" dur="1.501">要不要我送妳回去</text><text start="143.442" dur="1.7">不用了</text><text start="145.142" dur="1.4">还是我送你吧</text><text start="146.542" dur="1.666">一个大男人走在路上</text><text start="148.208" dur="1.967">危险</text><text start="150.175" dur="0.5">妳不要以为</text><text start="150.675" dur="1.201">妳在漆弹场上面救了我</text><text start="151.876" dur="1.966">就可以爬到我郑明威头上</text><text start="153.842" dur="0.5">我威哥</text><text start="154.342" dur="2.666">怎么可能要一个女生送呢</text><text start="158.975" dur="1.033">威哥</text><text start="160.008" dur="2.768">原来今天是雨晴救了你哦</text><text start="162.776" dur="2.132">难怪你今天表现那么好</text><text start="164.908" dur="1.167">就是说嘛</text><text start="166.075" dur="1.033">大家都住在一起</text><text start="167.108" dur="1.2">你送我、我送你</text><text start="168.308" dur="2.301">有什么不一样啊</text><text start="170.609" dur="1.432">毛玲玲，这么晚了</text><text start="172.041" dur="0.867">妳要怎么回去啊</text><text start="172.908" dur="1.467">要不要我送妳</text><text start="174.375" dur="0.767">威哥</text><text start="175.142" dur="1.799">为什么你没有问我们两个啊</text><text start="176.941" dur="1.835">因为还没有轮到妳们两个啊</text><text start="178.776" dur="1.366">妳长得这么像龙猫</text><text start="180.142" dur="1.133">那么安全</text><text start="181.275" dur="1">妳跟在龙猫旁边</text><text start="182.275" dur="1.9">怎么会危险呢</text><text start="184.175" dur="2.267">不用人送，我自己回去就好了</text><text start="187.175" dur="1.434">毛玲玲</text><text start="188.609" dur="1.666">威哥，算了啦</text><text start="190.275" dur="2.666">反正班长可以自己回去啊</text><text start="192.941" dur="2.067">郑明威，先撤了</text><text start="196.842" dur="1.934">威哥，我们现在要赶快回去啦</text><text start="198.776" dur="0.833">你知道为什么吗</text><text start="199.609" dur="2">因为快十点了</text><text start="201.609" dur="1.566">十点肚脐要查房</text><text start="203.175" dur="3.367">我们再不回去的话会人道毁灭</text><text start="206.542" dur="1">对啊，郑明威</text><text start="207.542" dur="2.2">不要害我们被杜组长骂</text><text start="209.742" dur="0.833">快点... 好... </text><text start="210.575" dur="1.167">走... </text><text start="211.742" dur="1.566">走...快走</text><text start="215.509" dur="1.133">不好了</text><text start="216.642" dur="0.633">天啊</text><text start="217.275" dur="2.033">我可以再吃一点</text><text start="219.308" dur="0.434">真的</text><text start="219.742" dur="1.9">对啊</text><text start="222.809" dur="0.6">完蛋了</text><text start="223.409" dur="2.333">锁起来了</text><text start="225.742" dur="1.166">锁起来了</text><text start="226.908" dur="1.367">我们的门禁时间快到了</text><text start="228.275" dur="1.067">怎么办啊</text><text start="229.342" dur="0.8">对啊</text><text start="230.142" dur="1.267">爬墙</text><text start="231.409" dur="1.632">走</text><text start="234.709" dur="0.533">等一下</text><text start="235.242" dur="0.634">来</text><text start="235.876" dur="1.065">好，来</text><text start="236.941" dur="1.234">好，来了哦</text><text start="238.175" dur="0.9">来哦</text><text start="239.075" dur="1.267">前脚就好... </text><text start="240.342" dur="0.833">好，来... </text><text start="241.175" dur="1.701">一、二、三，来</text><text start="243.642" dur="0.433">干嘛</text><text start="244.075" dur="0.534">干什么</text><text start="244.609" dur="0.9">马...马桶</text><text start="245.509" dur="0.833">宝贝... </text><text start="246.342" dur="0.866">干嘛... 宝贝</text><text start="247.208" dur="0.634">你出来一点</text><text start="247.842" dur="1.733">左边一点，对</text><text start="249.575" dur="2.633">你有没有洗澡啊</text><text start="252.208" dur="0.967">干嘛啦</text><text start="253.175" dur="0.766">再换脚</text><text start="253.941" dur="0.668">你左脚先</text><text start="254.609" dur="1">好... </text><text start="255.609" dur="0.9">左脚上</text><text start="256.509" dur="0.966">这一只</text><text start="257.475" dur="1.401">来，一、二、三</text><text start="258.876" dur="1.833">快啦</text><text start="263.475" dur="1.067">快下去了</text><text start="264.542" dur="1.6">好...来</text><text start="268.542" dur="1.733">我们换个姿势好了</text><text start="270.275" dur="1.467">好... </text><text start="271.742" dur="1.1">我背你</text><text start="272.842" dur="0.567">来哦</text><text start="273.409" dur="0.766">一、二... </text><text start="274.175" dur="1.667">一、二、三，上</text><text start="276.809" dur="1.199">包贝尔</text><text start="278.008" dur="1.3">开门啦</text><text start="279.308" dur="1.967">好累哦，马桶</text><text start="281.275" dur="1.867">宝贝，你帮忙</text><text start="283.142" dur="2.166">一、二、三</text><text start="285.308" dur="0.568">再来</text><text start="285.876" dur="1.199">一、二、三</text><text start="287.075" dur="1.033">好，等一下</text><text start="288.108" dur="1.1">腰有一点酸</text><text start="289.208" dur="0.967">再一次</text><text start="290.175" dur="1.133">马桶，来</text><text start="291.308" dur="0.967">准备好了吗</text><text start="292.275" dur="1.434">包贝尔，你要帮忙，快点</text><text start="293.709" dur="0.666">来了</text><text start="294.375" dur="2.566">一、二、三</text><text start="296.941" dur="2.468">马桶，你还要多久啊</text><text start="299.409" dur="1.566">快一点啦</text><text start="300.975" dur="1.966">一、二... </text><text start="302.941" dur="1.701">人呢</text><text start="305.275" dur="1.666">威哥</text><text start="306.941" dur="2.034">我等一下还要洗内裤</text><text start="308.975" dur="1.834">威哥，我们想要洗澡了</text><text start="310.809" dur="2.399">郑明威，就叫你多用点脑</text><text start="313.208" dur="1.067">门是可以开的</text><text start="314.275" dur="1.367">晚安了</text><text start="315.642" dur="1.399">拜拜</text><text start="317.041" dur="1.634">原来门是妳开的哦</text><text start="318.675" dur="1.4">讨厌</text><text start="324.642" dur="1.8">马桶、宝贝</text><text start="328.008" dur="4.567">宝贝... </text><text start="368.809" dur="1.533">主任，你放心</text><text start="370.342" dur="0.467">我们班</text><text start="370.809" dur="1.566">一定会好好照顾新同学的</text><text start="372.375" dur="2">而且会照顾到无微不至哦</text><text start="375.742" dur="1.166">那就好... </text><text start="376.908" dur="1.334">你不要欺负人家哦</text><text start="378.242" dur="0.866">肯定不会</text><text start="379.108" dur="1.9">一定疼爱有加哦</text><text start="381.008" dur="0.967">郑明威</text><text start="381.975" dur="3.767">你对新同学还满热情的嘛</text><text start="385.742" dur="2.199">我本来就热爱打抱不平啊</text><text start="387.941" dur="3.401">而且和乐好相处</text><text start="393.375" dur="1.367">不要踢我</text><text start="394.742" dur="2.134">对不起，我脚太长了</text><text start="396.876" dur="2.232">郑明威，不要捣乱</text><text start="399.308" dur="2.134">其实郑明威只是爱耍帅</text><text start="401.442" dur="1.9">逞英雄、伸张正义</text><text start="403.342" dur="0.5">有的时候</text><text start="403.842" dur="1.833">他还满顾虑别人的感受的</text><text start="405.675" dur="1.9">妳不用替他说话</text><text start="407.575" dur="1.333">反正到时候他弄我</text><text start="408.908" dur="1.567">我就见招拆招</text><text start="410.475" dur="1.7">不让他有机会的</text><text start="413.742" dur="2.266">程雨晴，这么晚了</text><text start="416.008" dur="1.067">妳对宿舍也不了解</text><text start="417.075" dur="1.133">要不要我送妳回去</text><text start="418.208" dur="1.668">不用了</text><text start="419.876" dur="1.399">还是我送你们</text><text start="421.275" dur="3.601">一个大男人走在路上危险</text><text start="424.876" dur="0.366">妳不要以为</text><text start="425.242" dur="1.433">妳在漆弹场上面救了我</text><text start="426.675" dur="1.9">就可以爬到我郑明威头上</text><text start="428.575" dur="0.366">我威哥</text><text start="428.941" dur="1.734">怎么可能要一个女生送呢</text><text start="443.409" dur="2.066">你怎么会在这里啊</text><text start="447.075" dur="2.534">我答应郑明威要送妳回家</text><text start="450.709" dur="1.033">不用啦</text><text start="451.742" dur="2.067">我自己回去就好了</text><text start="454.609" dur="1.033">好啦</text><text start="455.642" dur="2">妳如果不想要旁边有人陪的话</text><text start="457.642" dur="2.366">我就退后两步</text><text start="460.008" dur="1.834">而且现在天色也晚了</text><text start="461.842" dur="2.633">妳一个人在外面很危险</text><text start="464.475" dur="1.934">我没有看到妳安全进家门</text><text start="466.409" dur="1.266">我不放心</text><text start="487.041" dur="2.201">真是的</text><text start="491.175" dur="2.9">干嘛上什么漆弹课啦</text><text start="494.075" dur="3.334">叫马桶挡子弹没有屁用</text><text start="497.409" dur="1.166">妳看妳</text><text start="498.575" dur="1.167">叫妳运动吧</text><text start="499.742" dur="1.134">妳就不运动</text><text start="500.876" dur="1.499">我有运动好吗</text><text start="502.375" dur="1.566">妳哪有啊</text><text start="503.941" dur="1.201">妳没有看到我每天晚上</text><text start="505.142" dur="2.433">上网做眼球运动吗</text><text start="507.575" dur="1.8">眼球运动</text><text start="509.375" dur="1.6">那妳每天晚上吃东西</text><text start="510.975" dur="2.1">该不会这个叫作胃部运动吧</text><text start="513.075" dur="1.434">这也是一个</text><text start="514.509" dur="0.766">妳有毛病啊</text><text start="515.275" dur="1.067">哪有啊</text><text start="516.342" dur="1.866">那这给妳</text><text start="519.609" dur="1.432">贴布</text><text start="522.742" dur="1.166">好香哦</text><text start="523.908" dur="2.501">虽然我是燕子，不是蜈蚣</text><text start="526.409" dur="2.666">但我不随便受禄哦</text><text start="530.542" dur="1.499">飞燕</text><text start="532.041" dur="1">妳应该知道</text><text start="533.041" dur="1.568">无功不受禄的无功</text><text start="534.609" dur="1.167">跟在地上爬的蜈蚣</text><text start="535.776" dur="1.957">是不一样的吧</text><text start="537.765" dur="1.599">不要那么计较嘛</text><text start="539.364" dur="1.967">反正雨晴给我贴布</text><text start="541.331" dur="1.8">那我一定要回礼了</text><text start="545.83" dur="1.134">对了</text><text start="546.964" dur="1.833">这个给妳，黑面膜</text><text start="548.797" dur="2.1">心洁给我的，非常好用哦</text><text start="553.197" dur="2.234">雨晴，妳皮肤这么好</text><text start="555.431" dur="1.566">应该也不太需要用面膜吧</text><text start="556.997" dur="0.933">当然需要</text><text start="557.93" dur="1.768">我也想变漂亮嘛</text><text start="559.698" dur="1.6">谢谢</text><text start="561.298" dur="0.899">妳在干嘛</text><text start="562.197" dur="1.134">我在学雨晴</text><text start="563.331" dur="1.733">把贴布剪成心形的形状</text><text start="565.064" dur="2.601">妳不觉得这样很可爱吗</text><text start="567.665" dur="1.833">赞哦</text><text start="569.498" dur="1.866">还好雨晴很好相处</text><text start="571.364" dur="1.301">等言馨回来了</text><text start="572.665" dur="2.966">想必一定每天都很热闹</text><text start="575.631" dur="2.566">感觉妳们感情都很好哦</text><text start="578.197" dur="1.067">当然啰</text><text start="579.765" dur="1.633">我给妳看言馨的照片好不好</text><text start="583.431" dur="1.334">妳看</text><text start="584.765" dur="2.032">她是一个很讲义气的女生哦</text><text start="586.797" dur="1.1">只要班上同学有事</text><text start="587.897" dur="1.467">她一定第一个站出来</text><text start="589.364" dur="1.833">对啊，我觉得妳和她一定很合</text><text start="591.197" dur="1.301">因为在女生里面</text><text start="592.498" dur="0.766">带头呛威哥的</text><text start="593.264" dur="1.666">就是言馨了</text><text start="594.93" dur="1.801">跟郑明威对呛哦</text><text start="605.964" dur="3.534">威哥，有人在想你哦</text><text start="609.498" dur="1.432">想我</text><text start="610.93" dur="1.735">我看是有人在骂我</text><text start="613.665" dur="1.966">一定是程雨晴那个家伙</text><text start="615.631" dur="1.667">威哥，你跟程雨晴</text><text start="617.298" dur="1.433">到底什么关系啊</text><text start="618.731" dur="1.934">为什么她要在漆弹场上救你啊</text><text start="620.665" dur="0.866">对啊</text><text start="621.531" dur="1.566">没关系</text><text start="623.097" dur="2.668">首先是她鸡婆</text><text start="625.765" dur="1.966">再来她不用救我</text><text start="627.731" dur="1.733">我自己也躲得过好不好</text><text start="629.464" dur="1.333">是这样吗</text><text start="630.797" dur="1.567">当然</text><text start="632.364" dur="1.667">不是啊</text><text start="634.031" dur="1.367">每次你只要遇到女人</text><text start="635.398" dur="1.733">就会对兄弟撒谎</text><text start="637.131" dur="1.933">像上次遇到叫小贺的时候</text><text start="639.064" dur="0.9">你还跟我们说什么</text><text start="639.964" dur="0.933">她想跟你要通讯软体</text><text start="640.897" dur="1.2">结果你不想给她</text><text start="642.097" dur="1.534">结果根本没有这些事情嘛</text><text start="643.631" dur="1.5">对...说谎精</text><text start="645.131" dur="2.233">我哪有啊</text><text start="647.364" dur="1.867">好啊，那你告诉我</text><text start="649.231" dur="2.766">程雨晴她是女人吗</text><text start="651.997" dur="1.933">的确不像个女人耶</text><text start="653.93" dur="1.835">知我者马桶也</text><text start="655.765" dur="1.866">那是因为她太MAN啦</text><text start="657.631" dur="1.5">对... </text><text start="660.031" dur="1.899">其实这阵子相处下来</text><text start="661.93" dur="2.101">她人还不错</text><text start="664.031" dur="0.799">我现在有点后悔</text><text start="664.83" dur="1.601">那时候跟她打躲避球</text><text start="666.431" dur="2.733">我和你跟她打那么认真</text><text start="669.164" dur="0.766">包贝尔</text><text start="669.93" dur="1.701">你现在是窝里反痛耶</text><text start="671.631" dur="0.4">是不是</text><text start="672.031" dur="1.066">轻一点... </text><text start="673.097" dur="2.234">什么叫窝里反</text><text start="675.331" dur="0.967">我告诉你们哦</text><text start="676.298" dur="1.632">你们谁都不可以喜欢程雨晴</text><text start="677.93" dur="1.634">为什么</text><text start="679.564" dur="0.8">程雨晴在学校</text><text start="680.364" dur="1.934">这么多肤浅的男生在追</text><text start="682.298" dur="0.899">如果你们追的话</text><text start="683.197" dur="1.867">不就跟着一样肤浅</text><text start="685.064" dur="1.567">再说之前她怎么对付我</text><text start="686.631" dur="1.633">你们又不是不知道</text><text start="688.264" dur="2.467">谁跟她好就是跟我不好</text><text start="690.731" dur="1.567">就不是兄弟</text><text start="692.298" dur="2.4">还好我一直爱的都是贾飞燕</text><text start="694.698" dur="1.433">哪有这样的啦</text><text start="696.131" dur="1.966">就是这样啦</text><text start="698.097" dur="0.568">所以你们知道</text><text start="698.665" dur="1.733">现在该怎么做了吧</text><text start="700.398" dur="1.2">我知道了</text><text start="701.598" dur="0.7">威哥</text><text start="702.298" dur="1.699">所以我们是要改当姊妹对不对</text><text start="703.997" dur="1.967">下午茶</text><text start="709.83" dur="2">不要吃就不要吃，我自己吃</text><text start="716.298" dur="0.933">赶快啊</text><text start="717.231" dur="0.933">同学，脚步加快</text><text start="718.164" dur="1.933">还慢吞吞啊</text><text start="720.097" dur="1.1">还有你那个扣子扣起来</text><text start="721.197" dur="0.867">你没有那么壮</text><text start="722.064" dur="0.967">扣起来</text><text start="723.031" dur="0.833">教官早对</text><text start="723.864" dur="0.434">同学早</text><text start="724.298" dur="1.933">还有十秒</text><text start="726.231" dur="4.9">九、八、七、六</text><text start="731.131" dur="4.799">五、四、三、二、一</text><text start="735.93" dur="1.201">停</text><text start="737.797" dur="4.234">白兆亿，你又迟到了一秒</text><text start="742.031" dur="0.933">来</text><text start="742.964" dur="0.534">组长</text><text start="743.498" dur="0.699">是</text><text start="744.197" dur="1.967">那是因为我们班导有教过我们</text><text start="746.164" dur="1.933">做人要厚道</text><text start="748.097" dur="1.201">厚道</text><text start="750.364" dur="1.401">所以呢</text><text start="751.765" dur="1.432">就后到啊</text><text start="753.197" dur="0.9">后面一点到</text><text start="754.097" dur="1.668">这个后到不是那个厚道</text><text start="755.765" dur="1.399">你还给我装傻啊</text><text start="757.164" dur="0.733">我误会了</text><text start="757.897" dur="2.2">还误会呢</text><text start="760.097" dur="1.201">大包、小包的</text><text start="761.298" dur="1.499">有没有带违禁品啊</text><text start="762.797" dur="0.834">绝对没有</text><text start="763.631" dur="1.8">组长，你可以搜</text><text start="765.431" dur="0.933">来，检查一下</text><text start="766.364" dur="1.067">上次就跟你说了</text><text start="767.431" dur="2">真的，组长，你检查看看</text><text start="769.431" dur="2.1">又是吃的</text><text start="771.531" dur="0.399">白兆亿</text><text start="771.93" dur="0.867">你能不能跟我解释一下</text><text start="772.797" dur="2.234">你带这个洗发精来干什么</text><text start="775.031" dur="1.066">你不要以为我不知道哦</text><text start="776.097" dur="2">这一罐外面现在卖到缺货</text><text start="778.097" dur="0.534">你是不是带来</text><text start="778.631" dur="1.4">要图利美容科的同学</text><text start="780.031" dur="2.166">组长，你误会了啦</text><text start="782.197" dur="1.234">这个是因为我们社团课</text><text start="783.431" dur="1.1">需要用到</text><text start="784.531" dur="1.399">我才带来的啊</text><text start="785.93" dur="0.501">对啊</text><text start="786.431" dur="1.167">所以是你自己要用的</text><text start="787.598" dur="0.599">没有错</text><text start="788.197" dur="0.8">这是教材</text><text start="788.997" dur="1.334">教材</text><text start="790.331" dur="1.133">教材</text><text start="795.598" dur="0.433">白兆亿</text><text start="796.031" dur="0.634">能不能解释一下</text><text start="796.665" dur="2.199">带沐浴乳来学校是干什么呢</text><text start="798.864" dur="2">这一罐也是我要用的</text><text start="800.864" dur="1.233">像现在我们有时候</text><text start="802.097" dur="1.267">体育课、游泳课</text><text start="803.364" dur="1.466">流汗嘛，会臭</text><text start="804.83" dur="0.901">所以我们就用这一罐</text><text start="805.731" dur="0.733">非常好用</text><text start="806.464" dur="2.167">从头到脚一罐搞定</text><text start="808.631" dur="1.233">运动型男在用的</text><text start="809.864" dur="1.3">组长，跟你非常像</text><text start="811.164" dur="0.867">帅</text><text start="812.031" dur="0.933">这你拍的广告对不对</text><text start="812.964" dur="1.5">你敢讲，我还不敢听呢</text><text start="814.464" dur="1.366">他是老外啊</text><text start="815.83" dur="1.601">好了，不要拍马屁了</text><text start="817.431" dur="0.967">赶快进去上课</text><text start="818.398" dur="1.532">谢谢组长</text><text start="821.031" dur="1.899">现在的学生真的有病</text><text start="827.897" dur="2.434">其他东西也检查过了吗</text><text start="831.031" dur="0.899">我大概看了一下</text><text start="831.93" dur="1.634">应该是没问题</text><text start="833.564" dur="1.9">大概看了一下</text><text start="836.231" dur="1.1">你既然怀疑学生</text><text start="837.331" dur="1.499">也把学生拦了下来</text><text start="838.83" dur="1.701">就应该要彻底检查</text><text start="840.531" dur="1.9">像你这样随便检查两、三下</text><text start="842.431" dur="1.833">毫无意义</text><text start="844.264" dur="0.633">好</text><text start="844.897" dur="1.234">杜组长</text><text start="846.131" dur="3.333">可不可以请你以后不要再来</text><text start="855.964" dur="1.833">妳昨天有没有被打到</text><text start="857.797" dur="1.234">我被打到超痛的</text><text start="859.031" dur="0.966">这里有瘀青吗</text><text start="859.997" dur="1.301">有</text><text start="861.298" dur="1">飞燕</text><text start="862.298" dur="1.666">妳怎么贴那么多贴布啊</text><text start="863.964" dur="0.667">对啊</text><text start="864.631" dur="1.1">妳要不要干脆剪个月亮</text><text start="865.731" dur="1.066">贴在额头上啊</text><text start="866.797" dur="1.868">这样妳会长得很像包公哦</text><text start="868.665" dur="0.933">我额头又不酸不痛</text><text start="869.598" dur="1.133">干嘛贴啊</text><text start="870.731" dur="0.934">好笑啊</text><text start="872.164" dur="0.733">你们不懂啦</text><text start="872.897" dur="1.167">不觉得我跟卡通猫</text><text start="874.064" dur="1.3">长得一模一样吗</text><text start="875.364" dur="1.334">卡通猫</text><text start="876.698" dur="1.6">妳知道卡通猫是无嘴猫吗</text><text start="878.298" dur="0.966">我知道</text><text start="879.264" dur="1.3">妳是贾飞燕耶</text><text start="880.564" dur="0.8">妳没有嘴</text><text start="881.364" dur="1.034">妳有办法进食吗</text><text start="882.398" dur="0.933">妳这样会不会饿死</text><text start="883.331" dur="0.7">妳这样进... </text><text start="884.031" dur="1.667">麦克强，你呛什么啦</text><text start="885.698" dur="1.533">我的意思是说</text><text start="887.231" dur="2.8">我跟卡通猫长得一样可爱</text><text start="891.064" dur="1.5">对了，嘉嘉、一美</text><text start="892.564" dur="2.201">妳们昨天打漆弹不会酸痛吗</text><text start="894.765" dur="1.466">要不要一起贴贴布啊</text><text start="896.231" dur="1.033">好啊</text><text start="897.264" dur="2.334">这是雨晴给我的耶</text><text start="899.598" dur="0.933">贾飞燕</text><text start="900.531" dur="2.466">该不会把我送妳的都用完了吧</text><text start="902.997" dur="2.401">没有，当然有留一点啦</text><text start="906.364" dur="1.6">你们要吗，我有很多</text><text start="907.964" dur="0.801">好啊</text><text start="908.765" dur="1.332">打漆弹的时候脚好酸哦</text><text start="910.097" dur="1.034">对啊，贴一下</text><text start="911.131" dur="1.167">我背满酸的给我一片</text><text start="913.531" dur="1.533">谢谢</text><text start="915.064" dur="0.866">好可爱哦</text><text start="916.564" dur="1.934">这造型跟妳不一样耶</text><text start="924.464" dur="1.034">曹教官很奇怪</text><text start="925.498" dur="1.399">叫我不要再去了</text><text start="926.897" dur="2.267">不要再去是什么意思</text><text start="929.164" dur="1.833">打我枪啊</text><text start="930.997" dur="0.833">拒绝我</text><text start="932.897" dur="0.933">问题是我都还没表白</text><text start="933.83" dur="1.935">有什么好拒绝的</text><text start="935.765" dur="0.833">真是的</text><text start="938.298" dur="3.566">我知道了... </text><text start="941.864" dur="1.4">她在暗示我</text><text start="943.264" dur="2.367">是她怕我累</text><text start="945.631" dur="1.633">还没有公开</text><text start="947.264" dur="0.666">不要这么... </text><text start="947.93" dur="2.867">这样子大剌剌的让大家看到</text><text start="950.797" dur="0.968">也对</text><text start="951.765" dur="3.032">到时候我就请她吃个饭</text><text start="954.797" dur="1.801">吃个饭、看个电影</text><text start="956.598" dur="1.433">看电影，再看个夜景</text><text start="958.031" dur="1.5">看... </text><text start="959.531" dur="1.867">你干嘛啦</text><text start="961.398" dur="0.399">熊主任</text><text start="961.797" dur="0.901">你吓到我了，知不知道</text><text start="962.698" dur="0.8">你进来也不敲个门</text><text start="963.498" dur="2.466">也...也不说个哈啰啊</text><text start="965.964" dur="0.534">哈啰</text><text start="966.498" dur="0.866">太晚了嘛</text><text start="967.364" dur="1.8">已经吓到我了</text><text start="969.164" dur="1.8">你干嘛闷不吭声坐在这边呢</text><text start="970.964" dur="1.2">我刚进来的时候</text><text start="972.164" dur="1.9">听到你说吃饭的事情</text><text start="974.064" dur="0.967">进行得怎么样了</text><text start="975.031" dur="1.166">嘘</text><text start="976.197" dur="1.667">你小声一点好不好</text><text start="977.864" dur="1.167">还没</text><text start="979.031" dur="0.567">你这样大声嚷嚷</text><text start="979.598" dur="1.466">要是人家听到了、知道</text><text start="981.064" dur="1.866">我...我丢脸嘛</text><text start="982.93" dur="1.368">不好意思</text><text start="984.298" dur="1">有什么好不好意思的啊</text><text start="985.298" dur="0.866">我都几岁了</text><text start="986.164" dur="0.501">我还在那边... </text><text start="986.665" dur="1.532">还在追女孩子</text><text start="988.197" dur="1.334">单身男女互相喜欢</text><text start="989.531" dur="2">是很正常的事情</text><text start="991.531" dur="1.733">除非对方已婚</text><text start="993.264" dur="1.666">没有，对方没... </text><text start="999.564" dur="0.9">她没有已婚</text><text start="1000.464" dur="0.834">她单身</text><text start="1001.298" dur="0.499">她真的单身</text><text start="1001.797" dur="0.534">百分之百单身</text><text start="1002.331" dur="0.499">我就是确定</text><text start="1002.83" dur="1.134">我才追她的嘛</text><text start="1003.964" dur="0.5">你怎么会... </text><text start="1004.464" dur="2.301">你怎么会讲什么... </text><text start="1006.765" dur="0.9">单身就好啦</text><text start="1007.665" dur="1.199">那你更不用紧张啊</text><text start="1008.864" dur="0.4">我... </text><text start="1009.264" dur="1.334">又不是这个人在我们学校</text><text start="1010.598" dur="1.466">对不对</text><text start="1012.665" dur="0.866">谁跟你说的</text><text start="1013.531" dur="1.6">谁告诉你，讲</text><text start="1016.264" dur="2.234">不是</text><text start="1018.498" dur="0.766">不是... </text><text start="1019.264" dur="2.633">我不是那个意思</text><text start="1021.897" dur="0.734">你怎么会... </text><text start="1022.631" dur="2.299">你怎么会想这样子呢</text><text start="1024.93" dur="1.301">我杜有德是那种人吗</text><text start="1026.231" dur="1.267">我是吗</text><text start="1027.498" dur="1">我忙学校学生的事情</text><text start="1028.498" dur="0.666">我就忙不过来</text><text start="1029.164" dur="2.633">我怎么可能去勾搭教职员嘛</text><text start="1031.797" dur="0.767">熊主任，你... </text><text start="1032.564" dur="1">你看我... </text><text start="1033.564" dur="2.167">我是那种人吗</text><text start="1035.731" dur="1.433">杜组长</text><text start="1037.164" dur="2.933">是不是我们学校的人不重要</text><text start="1040.097" dur="1.733">重点是动作要快一点</text><text start="1041.83" dur="1.334">你要约她出来吃饭</text><text start="1043.164" dur="0.7">我们才可以讨论</text><text start="1043.864" dur="1.4">下一步要做什么</text><text start="1045.264" dur="1.134">我才能帮你啊</text><text start="1047.197" dur="1.134">我...我也想</text><text start="1048.331" dur="1.866">我也想快点约</text><text start="1050.197" dur="1.468">好啦，我...我尽快</text><text start="1051.665" dur="0.866">你放心</text><text start="1052.531" dur="0.8">我碰到什么问题</text><text start="1053.331" dur="0.766">我会跟你讲</text><text start="1054.097" dur="1.434">我会请教你的意见</text><text start="1055.531" dur="2.234">你是我私人的军师</text><text start="1057.765" dur="0.933">好不好</text><text start="1058.698" dur="1.299">还有</text><text start="1059.997" dur="1.167">不要讲出去</text><text start="1061.164" dur="1.733">不要什么事情都大声嚷嚷</text><text start="1062.897" dur="0.9">好不好</text><text start="1063.797" dur="1.033">你为什么每件事情</text><text start="1064.83" dur="1.234">都喜欢大声嚷嚷呢</text><text start="1066.064" dur="2.2">坏习惯，你要改掉</text><text start="1068.264" dur="1.467">好，但是你动作快一点</text><text start="1069.731" dur="0.533">好</text><text start="1070.264" dur="1.367">好</text><text start="1071.631" dur="0.867">好啦</text><text start="1079.83" dur="1.501">吃饭、看电影</text><text start="1083.741" dur="1.7">可是我比较喜欢吃蓝莓面包</text><text start="1087.207" dur="0.734">没有耶</text><text start="1087.941" dur="0.7">那我先给你好了</text><text start="1088.641" dur="2.933">好啊</text><text start="1091.574" dur="1.134">那妳早餐吃什么啊</text><text start="1092.708" dur="1.466">我喜欢吃萝卜糕</text><text start="1094.174" dur="0.667">有加蛋吗</text><text start="1094.841" dur="1.666">没有</text><text start="1096.507" dur="1.067">加蛋很好吃啊</text><text start="1097.574" dur="1.1">加蛋要多五块耶</text><text start="1098.674" dur="1.733">要配蛋饼</text><text start="1101.008" dur="1.6">蛋饼就要点两份了啊</text><text start="1103.441" dur="2.666">飞燕，这给妳</text><text start="1106.107" dur="0.734">为什么</text><text start="1106.841" dur="0.566">没有啦</text><text start="1107.407" dur="1.867">就我逛街的时候刚好看到</text><text start="1109.274" dur="1.434">就顺手买啦</text><text start="1110.708" dur="0.833">而且妳不是说</text><text start="1111.541" dur="2.2">这个牌子的润喉丸很好用吗</text><text start="1113.741" dur="1">是很好用啊</text><text start="1114.741" dur="1.967">那这给妳，我多买的</text><text start="1116.708" dur="1">真的吗</text><text start="1117.708" dur="0.833">谢谢哦</text><text start="1122.874" dur="1.134">我想得没错</text><text start="1124.008" dur="1.067">只要付出</text><text start="1125.075" dur="2.099">大家一定会继续跟我当朋友的</text><text start="1136.008" dur="0.933">这件我有耶</text><text start="1136.941" dur="0.833">好漂亮哦</text><text start="1137.774" dur="0.733">对啊</text><text start="1138.507" dur="1.034">还是妳下次借我穿</text><text start="1139.541" dur="0.599">好啊我也有耶</text><text start="1140.14" dur="0.801">那我借妳穿好了</text><text start="1140.941" dur="0.5">妳也有</text><text start="1141.441" dur="1">妳有</text><text start="1142.441" dur="1.233">其实我没有缺一些</text><text start="1143.674" dur="2.034">斗篷或是披风之类的东西</text><text start="1145.708" dur="2.833">妳知道吗怎么可以这样</text><text start="1148.541" dur="0.833">那个... </text><text start="1149.374" dur="1.601">我要去福利社一趟</text><text start="1150.975" dur="0.899">妳们要买什么</text><text start="1151.874" dur="0.8">我顺便买</text><text start="1152.674" dur="2.767">我不用，我不饿</text><text start="1155.441" dur="0.733">那... </text><text start="1156.174" dur="2.367">那妳帮我一瓶果汁好不好</text><text start="1158.541" dur="0.966">好，没问题</text><text start="1165.14" dur="1.734">妳们有没有觉得</text><text start="1166.874" dur="1.7">米淇好像有点怪怪的</text><text start="1168.574" dur="1.733">哪里怪怪的啊</text><text start="1170.774" dur="3.301">她是不是有点刻意在讨好我们</text><text start="1174.075" dur="1.766">有吗</text><text start="1175.841" dur="1.067">听妳这么一说</text><text start="1176.908" dur="1.299">我就想到今天早上</text><text start="1178.207" dur="2.2">她突然拿了一包润喉丸给我</text><text start="1180.407" dur="1.334">还说是要送给我的</text><text start="1181.741" dur="1.433">对不对</text><text start="1183.174" dur="1.267">她现在是不是觉得</text><text start="1184.441" dur="1.467">只要买点东西给我们</text><text start="1185.908" dur="3.399">就可以当作什么事都没有发生</text><text start="1189.941" dur="2.667">我觉得米淇也很可怜啊</text><text start="1192.608" dur="1.333">陈龙飞的事情</text><text start="1193.941" dur="0.967">罪魁祸首</text><text start="1194.908" dur="2.366">是那个二A班的玫琳</text><text start="1197.274" dur="3.334">米淇被威胁也算是受害者吧</text><text start="1200.608" dur="2.599">现在却要被大家冷落</text><text start="1204.841" dur="2.767">这样说也是没错啦</text><text start="1207.608" dur="1.866">但是如果真的没有鬼的话</text><text start="1209.474" dur="1.3">那她为什么不老实交代</text><text start="1210.774" dur="2.366">那天躲在吉他社外面的事情</text><text start="1213.14" dur="1.234">亏我们还把她当姊妹</text><text start="1214.374" dur="0.833">就是嘛</text><text start="1215.207" dur="0.734">我看她</text><text start="1215.941" dur="2.134">就已经在二A班当间谍了</text><text start="1218.075" dur="2.266">米淇不是那种人啦</text><text start="1220.341" dur="1.033">总之呢</text><text start="1221.374" dur="1.534">这段期间</text><text start="1222.908" dur="0.8">如果她还没有跟我们</text><text start="1223.708" dur="1.633">好好交代清楚的话</text><text start="1225.341" dur="1.533">妳们都不能心软哦</text><text start="1226.874" dur="1.967">当作给她一点小小的惩罚</text><text start="1230.874" dur="1.4">另外这件好适合妳哦</text></transcript>